deepzoom/apps.py
deepzoom/models.py
deepzoom/admin.py
deepzoom/mixins.py
deepzoom/utils.py
deepzoom/__init__.py
deepzoom/tests.py
deepzoom/deepzoom.py
deepzoom/signals.py
deepzoom/templates/deepzoom/deepzoom_js.html
deepzoom/templatetags/__init__.py
deepzoom/templatetags/deepzoom_tags.py
deepzoom/static/deepzoom/js/vendor/openseadragon/LICENSE.txt
deepzoom/static/deepzoom/js/vendor/openseadragon/openseadragon.min.js.map
deepzoom/static/deepzoom/js/vendor/openseadragon/openseadragon.min.js
deepzoom/static/deepzoom/js/vendor/openseadragon/images/zoomout_pressed.png
deepzoom/static/deepzoom/js/vendor/openseadragon/images/next_hover.png
deepzoom/static/deepzoom/js/vendor/openseadragon/images/rotateleft_pressed.png
deepzoom/static/deepzoom/js/vendor/openseadragon/images/fullpage_grouphover.png
deepzoom/static/deepzoom/js/vendor/openseadragon/images/previous_rest.png
deepzoom/static/deepzoom/js/vendor/openseadragon/images/next_rest.png
deepzoom/static/deepzoom/js/vendor/openseadragon/images/zoomin_pressed.png
deepzoom/static/deepzoom/js/vendor/openseadragon/images/fullpage_rest.png
deepzoom/static/deepzoom/js/vendor/openseadragon/images/next_grouphover.png
deepzoom/static/deepzoom/js/vendor/openseadragon/images/fullpage_hover.png
deepzoom/static/deepzoom/js/vendor/openseadragon/images/zoomin_rest.png
deepzoom/static/deepzoom/js/vendor/openseadragon/images/previous_grouphover.png
deepzoom/static/deepzoom/js/vendor/openseadragon/images/next_pressed.png
deepzoom/static/deepzoom/js/vendor/openseadragon/images/zoomin_hover.png
deepzoom/static/deepzoom/js/vendor/openseadragon/images/fullpage_pressed.png
deepzoom/static/deepzoom/js/vendor/openseadragon/images/rotateright_hover.png
deepzoom/static/deepzoom/js/vendor/openseadragon/images/home_grouphover.png
deepzoom/static/deepzoom/js/vendor/openseadragon/images/rotateleft_grouphover.png
deepzoom/static/deepzoom/js/vendor/openseadragon/images/rotateright_pressed.png
django_deepzoom-3.0.3.dist-info/top_level.txt
django_deepzoom-3.0.3.dist-info/RECORD
django_deepzoom-3.0.3.dist-info/DESCRIPTION.rst
django_deepzoom-3.0.3.dist-info/METADATA
django_deepzoom-3.0.3.dist-info/WHEEL
django_deepzoom-3.0.3.dist-info/metadata.json
